PyWaMG/PyWaMG.py
PyWaMG/__init__.py
PyWaMG-1.1.3.dist-info/METADATA
PyWaMG-1.1.3.dist-info/WHEEL
PyWaMG-1.1.3.dist-info/top_level.txt
PyWaMG-1.1.3.dist-info/RECORD
